werpy/__init__.py
werpy/errorhandler.py
werpy/metrics.cpython-311-x86_64-linux-gnu.so
werpy/normalize.py
werpy/py.typed
werpy/summary.py
werpy/summaryp.py
werpy/wer.py
werpy/werp.py
werpy/werps.py
werpy/wers.py
werpy-3.3.0.dist-info/LICENSE
werpy-3.3.0.dist-info/METADATA
werpy-3.3.0.dist-info/WHEEL
werpy-3.3.0.dist-info/RECORD
