Metadata-Version: 2.1
Name: werpy
Version: 3.3.0
Summary: A powerful yet lightweight Python package to calculate and analyze the Word Error Rate (WER).
Keywords: werpy,wer,word error rate,asr,automatic speech recognition,stt,speech-to-text,levenshtein distance,text similarity,nlp,accuracy metrics
Author-Email: Ross Armstrong <ross.armstrong@analyticsinmotion.com>
License: BSD 3-Clause License
Classifier: Programming Language :: Python :: 3
Classifier: Programming Language :: Python :: 3 :: Only
Classifier: Programming Language :: Python :: 3.10
Classifier: Programming Language :: Python :: 3.11
Classifier: Programming Language :: Python :: 3.12
Classifier: Programming Language :: Python :: 3.13
Classifier: Programming Language :: Python :: Implementation :: CPython
Classifier: License :: OSI Approved :: BSD License
Classifier: Operating System :: Microsoft :: Windows
Classifier: Operating System :: MacOS
Classifier: Operating System :: POSIX :: Linux
Classifier: Development Status :: 5 - Production/Stable
Classifier: Intended Audience :: Developers
Classifier: Topic :: Scientific/Engineering
Classifier: Topic :: Software Development
Classifier: Topic :: Text Processing
Classifier: Topic :: Scientific/Engineering :: Artificial Intelligence
Classifier: Topic :: Scientific/Engineering :: Mathematics
Project-URL: Repository, https://github.com/analyticsinmotion/werpy
Project-URL: Documentation, https://werpy.readthedocs.io/
Project-URL: Bug Tracker, https://github.com/analyticsinmotion/werpy/issues
Requires-Python: >=3.10
Requires-Dist: numpy>=1.26.0; python_version < "3.12"
Requires-Dist: numpy>=2.2.0; python_version >= "3.12"
Requires-Dist: pandas>=2.0.0
Provides-Extra: docs
Requires-Dist: sphinx==8.2.3; extra == "docs"
Requires-Dist: sphinx-nefertiti==0.9.1; extra == "docs"
Provides-Extra: test
Requires-Dist: pytest>=7.0.0; extra == "test"
Requires-Dist: pytest-cov>=4.0.0; extra == "test"
Provides-Extra: benchmarks
Requires-Dist: datasets>=4.4.1; extra == "benchmarks"
Requires-Dist: werx>=0.3.1; extra == "benchmarks"
Requires-Dist: jiwer>=4.0.0; extra == "benchmarks"
Requires-Dist: pywer>=0.1.1; extra == "benchmarks"
Requires-Dist: evaluate>=0.4.6; extra == "benchmarks"
Requires-Dist: universal-edit-distance>=0.4.3; extra == "benchmarks"
Requires-Dist: torchmetrics; extra == "benchmarks"
